[
    {
        "transactionName": "enterwebtours",
        "rawStartTime": 1700161107454,
        "rawEndTime": 1700161107751
    },
    {
        "transactionName": "login",
        "rawStartTime": 1700161107783,
        "rawEndTime": 1700161107986
    },
    {
        "transactionName": "Flights",
        "rawStartTime": 1700161108017,
        "rawEndTime": 1700161108218
    },
    {
        "transactionName": "FindFlight",
        "rawStartTime": 1700161108344,
        "rawEndTime": 1700161108500
    },
    {
        "transactionName": "ChuseFly",
        "rawStartTime": 1700161108530,
        "rawEndTime": 1700161108640
    },
    {
        "transactionName": "Credintails",
        "rawStartTime": 1700161108670,
        "rawEndTime": 1700161108791
    },
    {
        "transactionName": "invoice",
        "rawStartTime": 1700161108823,
        "rawEndTime": 1700161108855
    },
    {
        "transactionName": "gotolist",
        "rawStartTime": 1700161108871,
        "rawEndTime": 1700161109092
    },
    {
        "transactionName": "Signoff",
        "rawStartTime": 1700161109124,
        "rawEndTime": 1700161109312
    },
    {
        "transactionName": "BP_webtours",
        "rawStartTime": 1700161107439,
        "rawEndTime": 1700161109328
    }
]