[
    {
        "stepId": "STEP86",
        "stepName": "Url: webtours",
        "infFile": "t1.inf",
        "time": 1700776883557
    },
    {
        "stepId": "STEP87",
        "stepName": "Url: sign up now",
        "infFile": "t2.inf",
        "time": 1700776883770
    },
    {
        "stepId": "STEP88",
        "stepName": "Submit Data: login.pl",
        "infFile": "t3.inf",
        "time": 1700776883952
    },
    {
        "stepId": "STEP89",
        "stepName": "Url: button_next.gif",
        "infFile": "t4.inf",
        "time": 1700776884205
    },
    {
        "stepId": "STEP90",
        "stepName": "Url: SignOff Button",
        "infFile": "t5.inf",
        "time": 1700776884453
    }
]